miraheze/__init__.py
miraheze/version.py
miraheze/mediawiki/__init__.py
miraheze/mediawiki/check_read_only.py
miraheze/mediawiki/iaupload.py
miraheze/mediawiki/mwdeploy.py
miraheze/mediawiki/mwimport.py
miraheze/mediawiki/mwscript.py
miraheze/puppet/__init__.py
miraheze/puppet/cycle_puppet.py
miraheze/puppet/disable_puppet.py
miraheze/puppet/enable_puppet.py
miraheze/salt/__init__.py
miraheze/salt/utils.py
miraheze/salt/mwcli/__init__.py
miraheze/salt/mwcli/partial_reset_wiki.py
miraheze/salt/mwcli/rename_wiki.py
miraheze/swift/__init__.py
miraheze/swift/fix_container_permissions.py
tests/__init__.py
tests/test_iaupload.py
tests/test_mwdeploy.py
tests/test_mwimport.py
tests/test_mwscript.py
miraheze_pyutils-0.0.8.dist-info/LICENSE
miraheze_pyutils-0.0.8.dist-info/METADATA
miraheze_pyutils-0.0.8.dist-info/WHEEL
miraheze_pyutils-0.0.8.dist-info/entry_points.txt
miraheze_pyutils-0.0.8.dist-info/top_level.txt
miraheze_pyutils-0.0.8.dist-info/RECORD
